bratiaa/__init__.py
bratiaa/agree.py
bratiaa/agree_cli.py
bratiaa/evaluation.py
bratiaa/utils.py
bratsubset/annotation.py
bratsubset/common.py
bratsubset/config.py
bratsubset/message.py
bratsubset/projectconfig.py
bratsubset/realmessage.py
bratsubset/sosmessage.py
bratiaa-0.1.4.dist-info/LICENSE
bratiaa-0.1.4.dist-info/METADATA
bratiaa-0.1.4.dist-info/WHEEL
bratiaa-0.1.4.dist-info/entry_points.txt
bratiaa-0.1.4.dist-info/top_level.txt
bratiaa-0.1.4.dist-info/RECORD
