Metadata-Version: 2.1
Name: bratiaa
Version: 0.1.4
Summary: Inter-annotator agreement for Brat annotation projects
Home-page: https://github.com/kldtz/bratiaa
Author: Tobias Kolditz
Author-email: tbs.kldtz@gmail.com
License: UNKNOWN
Platform: UNKNOWN
Classifier: Programming Language :: Python :: 3
Classifier: License :: OSI Approved :: MIT License
Classifier: Operating System :: OS Independent
Requires-Python: >=3.6
Requires-Dist: numpy
Requires-Dist: matplotlib
Requires-Dist: pytest
Requires-Dist: scipy
Requires-Dist: tabulate
